estimators/__init__.py
estimators/database.py
estimators/datasets.py
estimators/estimators.py
estimators/evaluations.py
estimators/hashing.py
estimators-0.1.0.dev0.dist-info/DESCRIPTION.rst
estimators-0.1.0.dev0.dist-info/METADATA
estimators-0.1.0.dev0.dist-info/RECORD
estimators-0.1.0.dev0.dist-info/WHEEL
estimators-0.1.0.dev0.dist-info/metadata.json
estimators-0.1.0.dev0.dist-info/top_level.txt
tests/__init__.py
tests/conftest.py
tests/factories.py
tests/shared.py
tests/test_datasets.py
tests/test_estimators.py
tests/test_evaluations.py
