Metadata-Version: 2.0
Name: estimators
Version: 0.1.0.dev0
Summary: Machine Learning Version Control made Simple
Home-page: https://github.com/fridiculous/estimators
Author: Simon Frid
Author-email: simon.frid@gmail.com
License: MIT License
Keywords: scikit-learn,machine learning,ml,estimators,version control
Platform: UNKNOWN
Classifier: Environment :: Web Environment
Classifier: Development Status :: 3 - Alpha
Classifier: Framework :: IPython
Classifier: Intended Audience :: Developers
Classifier: Intended Audience :: Science/Research
Classifier: License :: OSI Approved :: MIT License
Classifier: Operating System :: OS Independent
Classifier: Programming Language :: Python
Classifier: Programming Language :: Python :: 3
Classifier: Programming Language :: Python :: 3.4
Classifier: Programming Language :: Python :: 3.5
Classifier: Topic :: Internet :: WWW/HTTP
Classifier: Topic :: Internet :: WWW/HTTP :: Dynamic Content
Classifier: Topic :: Scientific/Engineering :: Artificial Intelligence
Classifier: Topic :: Software Development :: Libraries :: Python Modules
Classifier: Topic :: Software Development :: Version Control
Requires-Dist: SQLAlchemy (==1.0.15)
Requires-Dist: pympler (==0.4.3)
